dexact/__init__.py
dexact/partition_state_pb2.py
dexact/server.py
dexact-0.1.4.dist-info/LICENSE
dexact-0.1.4.dist-info/METADATA
dexact-0.1.4.dist-info/WHEEL
dexact-0.1.4.dist-info/top_level.txt
dexact-0.1.4.dist-info/RECORD
