Metadata-Version: 2.1
Name: dexact
Version: 0.1.4
Summary: A very simple Python package which provides the necessary tools to interact with dexetera
Home-page: https://github.com/umbralcalc/dexact
Author: Robert J. Hardwick
Author-email: umbralcalc@gmail.com
License: UNKNOWN
Platform: UNKNOWN
Classifier: Programming Language :: Python :: 3
Classifier: License :: OSI Approved :: MIT License
Classifier: Operating System :: OS Independent
Requires-Python: >=3.6
License-File: LICENSE
Requires-Dist: protobuf
Requires-Dist: websockets
